KiCadRW/Geometry.py
KiCadRW/Objectifier.py
KiCadRW/Schema.py
KiCadRW/__init__.py
KiCadRW/Config/ConfigInstall.py
KiCadRW/Config/__init__.py
KiCadRW/Config/logging.yml
KiCadRW/Deprecated/Sexpression.py
KiCadRW/Deprecated/__init__.py
KiCadRW/Drawings/CircuitMacros.py
KiCadRW/Drawings/__init__.py
KiCadRW/Logging/__init__.py
KiCadRW/Tools/Path.py
KiCadRW/Tools/__init__.py
tasks/SECRET_CONFIG.py
tasks/__init__.py
tasks/anaconda.py
tasks/clean.py
tasks/doc.py
tasks/git.py
tasks/github.py
tasks/release.py
tasks/test.py
KiCadRW-0.1.dist-info/LICENSE.txt
KiCadRW-0.1.dist-info/METADATA
KiCadRW-0.1.dist-info/WHEEL
KiCadRW-0.1.dist-info/top_level.txt
KiCadRW-0.1.dist-info/RECORD
