Metadata-Version: 2.1
Name: KiCadRW
Version: 0.1
Summary: Python library to read/write KiCad Sexpr file format
Home-page: https://github.com/FabriceSalvaire/kicad-rw
Author: Fabrice Salvaire
Author-email: kicad-rw@fabrice-salvaire.fr
Maintainer: Fabrice Salvaire
Maintainer-email: kicad-rw@fabrice-salvaire.fr
License: GPLv3
Project-URL: Code, https://github.com/FabriceSalvaire/kicad-rw
Project-URL: Issue Tracker, https://github.com/FabriceSalvaire/kicad-rw/issues
Keywords: kicad,sexpr
Platform: any
Classifier: Topic :: Scientific/Engineering
Classifier: Intended Audience :: Education
Classifier: Development Status :: 5 - Production/Stable
Classifier: License :: OSI Approved :: GNU General Public License (GPL)
Classifier: Operating System :: OS Independent
Classifier: Programming Language :: Python :: 3.6
Requires-Python: >=3.6
Requires-Dist: PyYAML (>=5.3)
